setup.py
distributions_z1/Binomialdistribution.py
distributions_z1/Gaussiandistribution.py
distributions_z1/Generaldistribution.py
distributions_z1/__init__.py
distributions_z1.egg-info/PKG-INFO
distributions_z1.egg-info/SOURCES.txt
distributions_z1.egg-info/dependency_links.txt
distributions_z1.egg-info/not-zip-safe
distributions_z1.egg-info/top_level.txt