Metadata-Version: 1.0
Name: distributions-z1
Version: 0.1
Summary: Gaussian and Binomial distributions
Home-page: UNKNOWN
Author: Richmond Yeboah
Author-email: Richmond.k.yeboah@gmail.com
License: UNKNOWN
Platform: UNKNOWN
